databaseparsers/__init__.py
databaseparsers/openkim/README.md
databaseparsers/openkim/__init__.py
databaseparsers/openkim/__main__.py
databaseparsers/openkim/nomad_plugin.yaml
databaseparsers/openkim/parser.py
databaseparsers/openkim/metainfo/__init__.py
databaseparsers/openkim/metainfo/openkim.py
nomad_parser_plugins_database-1.1.3.dist-info/licenses/LICENSE.txt
nomad_parser_plugins_database-1.1.3.dist-info/METADATA
nomad_parser_plugins_database-1.1.3.dist-info/WHEEL
nomad_parser_plugins_database-1.1.3.dist-info/entry_points.txt
nomad_parser_plugins_database-1.1.3.dist-info/top_level.txt
nomad_parser_plugins_database-1.1.3.dist-info/RECORD
