Metadata-Version: 2.4
Name: nomad-parser-plugins-database
Version: 1.1.3
Summary: Collection of NOMAD parsers for databases.
Author: The NOMAD Authors
Project-URL: homepage, https://github.com/nomad-coe/database-parsers
License-File: LICENSE.txt
Requires-Dist: nomad-lab>=1.3.13
Requires-Dist: nomad-schema-plugin-simulation-workflow>=1.0.1
Requires-Dist: nomad-schema-plugin-run>=1.0.1
Requires-Dist: pydantic>=1.10.8
Provides-Extra: tests
Requires-Dist: pytest; extra == "tests"
Requires-Dist: pytest-cov; extra == "tests"
Requires-Dist: astroid>=2.5.1; extra == "tests"
Requires-Dist: mypy>=1.15; extra == "tests"
Requires-Dist: ruff; extra == "tests"
Requires-Dist: typing-extensions>=4.12; extra == "tests"
Dynamic: license-file
